jy_iiot_ruler_sdk/__init__.py
jy_iiot_ruler_sdk/base.py
jy_iiot_ruler_sdk/comm.py
jy_iiot_ruler_sdk/core.py
jy_iiot_ruler_sdk/device.py
jy_iiot_ruler_sdk/iot.py
jy_iiot_ruler_sdk/probe.py
jy_iiot_ruler_sdk-0.0.4.dist-info/METADATA
jy_iiot_ruler_sdk-0.0.4.dist-info/WHEEL
jy_iiot_ruler_sdk-0.0.4.dist-info/top_level.txt
jy_iiot_ruler_sdk-0.0.4.dist-info/RECORD
