Metadata-Version: 2.1
Name: jy-iiot-ruler-sdk
Version: 0.0.4
Summary: 精英物联网数据服务平台规则引擎轻代码开发SDK
Home-page: UNKNOWN
Author: RayWong
Author-email: wanglei@jylink.com
License: UNKNOWN
Platform: UNKNOWN
Classifier: Programming Language :: Python :: 3
Requires-Python: >=3.6
Requires-Dist: requests
